llama_index/readers/intercom/__init__.py
llama_index/readers/intercom/base.py
llama_index_readers_intercom-0.4.1.dist-info/METADATA
llama_index_readers_intercom-0.4.1.dist-info/WHEEL
llama_index_readers_intercom-0.4.1.dist-info/licenses/LICENSE
llama_index_readers_intercom-0.4.1.dist-info/RECORD
