Metadata-Version: 2.4
Name: llama-index-readers-intercom
Version: 0.4.1
Summary: llama-index readers intercom integration
Author-email: Your Name <you@example.com>
Maintainer: bbornsztein
License-Expression: MIT
License-File: LICENSE
Keywords: help center,intercom,knowledge base
Requires-Python: <4.0,>=3.9
Requires-Dist: llama-index-core<0.15,>=0.13.0
